pubgpy/__init__.py
pubgpy/api.py
pubgpy/client.py
pubgpy/enums.py
pubgpy/errors.py
pubgpy/leaderboards.py
pubgpy/mastery.py
pubgpy/matches.py
pubgpy/models.py
pubgpy/player.py
pubgpy/sample.py
pubgpy/season.py
pubgpy/tournaments.py
PUBGpy-1.1.dist-info/LICENSE
PUBGpy-1.1.dist-info/METADATA
PUBGpy-1.1.dist-info/WHEEL
PUBGpy-1.1.dist-info/top_level.txt
PUBGpy-1.1.dist-info/RECORD
